ppyPatternRecognition/__init__.py
ppyPatternRecognition/activation_function/__init__.py
ppyPatternRecognition/clustering/__init__.py
ppyPatternRecognition/clustering/kmeans.py
ppyPatternRecognition/clustering/simple_naive_bayes.py
ppyPatternRecognition/evaluation/__init__.py
ppyPatternRecognition/loss_function/__init__.py
ppyPatternRecognition/regression/__init__.py
ppyPatternRecognition/regression/base_regression.py
ppyPatternRecognition/regression/linear_regression.py
ppyPatternRecognition/regression/logistic_regression.py
ppyPatternRecognition-0.0.3.dist-info/LICENSE
ppyPatternRecognition-0.0.3.dist-info/METADATA
ppyPatternRecognition-0.0.3.dist-info/WHEEL
ppyPatternRecognition-0.0.3.dist-info/top_level.txt
ppyPatternRecognition-0.0.3.dist-info/RECORD
