Metadata-Version: 2.1
Name: ppyPatternRecognition
Version: 0.0.3
Summary: Pattern Recognition Package
Home-page: https://github.com/jirayuwat12/ppyPatternRecognition
Author: Jirayuwat Boonchan
Author-email: jirayuwat.dev@gmail.com
Classifier: Programming Language :: Python :: 3
Classifier: Operating System :: OS Independent
License-File: LICENSE
Requires-Dist: numpy
Requires-Dist: pandas
Requires-Dist: tqdm
